mkhelp/__init__.py
mkhelp/__main__.py
mkhelp/_base.py
mkhelp/_extended.py
mkhelp/_makefile_provider.py
mkhelp/_version.py
mkhelp/py.typed
mkhelp-0.2.1.dist-info/LICENSE
mkhelp-0.2.1.dist-info/METADATA
mkhelp-0.2.1.dist-info/WHEEL
mkhelp-0.2.1.dist-info/entry_points.txt
mkhelp-0.2.1.dist-info/top_level.txt
mkhelp-0.2.1.dist-info/RECORD
