Metadata-Version: 2.1
Name: mkhelp
Version: 0.2.1
Summary: Support for docstrings in makefiles
Classifier: License :: OSI Approved :: MIT License
Classifier: Programming Language :: Python :: 3
License-File: LICENSE
Requires-Dist: fire
